livapordata/__init__.py
livapordata/basics.py
livapordata/constants.py
livapordata/lithium.py
livapordata/transport.py
livapordata/utility.py
livapordata/vaporpressure.py
livapordata-0.9.1.dist-info/LICENSE.rst
livapordata-0.9.1.dist-info/METADATA
livapordata-0.9.1.dist-info/WHEEL
livapordata-0.9.1.dist-info/top_level.txt
livapordata-0.9.1.dist-info/RECORD
