Metadata-Version: 2.1
Name: livapordata
Version: 0.9.1
Summary: Literature data on lithium, especially its vapor
Home-page: https://github.com/cfe316/livapordata
Author: Jacob Schwartz
Author-email: jacobas@princeton.edu
License: UNKNOWN
Platform: UNKNOWN
Classifier: Development Status :: 4 - Beta
Classifier: Programming Language :: Python :: 3
Classifier: Operating System :: OS Independent
Classifier: Topic :: Scientific/Engineering :: Physics
Classifier: License :: OSI Approved :: BSD License
Classifier: Intended Audience :: Science/Research
Requires-Python: >=3.6
Requires-Dist: numpy (>=1.15)
Requires-Dist: scipy (>=1.2)
